shape2d/__init__.py
shape2d-0.0.dist-info/LICENSE
shape2d-0.0.dist-info/METADATA
shape2d-0.0.dist-info/WHEEL
shape2d-0.0.dist-info/top_level.txt
shape2d-0.0.dist-info/RECORD
